Chicoasen/__init__.py
Chicoasen/archivos.py
Chicoasen/bases_datos.py
Chicoasen-1.1.dist-info/METADATA
Chicoasen-1.1.dist-info/WHEEL
Chicoasen-1.1.dist-info/top_level.txt
Chicoasen-1.1.dist-info/RECORD
