Metadata-Version: 2.1
Name: Chicoasen
Version: 1.1
Summary: Librería para cargar archivos csv & json y conectar a una base de datos
Home-page: https://github.com/CIDETECSI/chicoasen
Author: Equipo SS
Author-email: mhernandezg2204@alumno.ipn.mx
License: MIT
Requires-Dist: pymupdf
